marshmallow_recipe/__init__.py
marshmallow_recipe/bake.py
marshmallow_recipe/fields.py
marshmallow_recipe/generics.py
marshmallow_recipe/hooks.py
marshmallow_recipe/metadata.py
marshmallow_recipe/missing.py
marshmallow_recipe/naming_case.py
marshmallow_recipe/options.py
marshmallow_recipe/py.typed
marshmallow_recipe/serialization.py
marshmallow_recipe/utils.py
marshmallow_recipe/validation.py
marshmallow_recipe-0.0.72.dist-info/METADATA
marshmallow_recipe-0.0.72.dist-info/WHEEL
marshmallow_recipe-0.0.72.dist-info/licenses/LICENSE
marshmallow_recipe-0.0.72.dist-info/RECORD
