Metadata-Version: 2.4
Name: marshmallow-recipe
Version: 0.0.72
Summary: Bake marshmallow schemas based on dataclasses
Project-URL: Homepage, https://github.com/anna-money/marshmallow-recipe
Author-email: Yury Pliner <yury.pliner@gmail.com>
License: MIT
License-File: LICENSE
Classifier: Development Status :: 5 - Production/Stable
Classifier: Intended Audience :: Developers
Classifier: License :: OSI Approved :: MIT License
Classifier: Operating System :: OS Independent
Classifier: Programming Language :: Python :: 3
Classifier: Programming Language :: Python :: 3 :: Only
Classifier: Programming Language :: Python :: 3.12
Classifier: Programming Language :: Python :: 3.13
Classifier: Programming Language :: Python :: 3.14
Requires-Python: >=3.12
Requires-Dist: marshmallow<4,>=2.20.5
Provides-Extra: dev
Requires-Dist: pyright==1.1.407; extra == 'dev'
Requires-Dist: pytest==8.3.5; extra == 'dev'
Requires-Dist: ruff==0.8.4; extra == 'dev'
Requires-Dist: setuptools; extra == 'dev'
